real_time_input/CONFIG.json
real_time_input/Client.py
real_time_input/RealTimeInput.py
real_time_input/__init__.py
real_time_input/__main__.py
kabbes_real_time_input-0.4.0.dist-info/LICENSE
kabbes_real_time_input-0.4.0.dist-info/METADATA
kabbes_real_time_input-0.4.0.dist-info/WHEEL
kabbes_real_time_input-0.4.0.dist-info/top_level.txt
kabbes_real_time_input-0.4.0.dist-info/RECORD
