Metadata-Version: 2.1
Name: kabbes-real-time-input
Version: 0.4.0
Summary: Python function for getting real time inputs from the user
Home-page: https://pypi.org/project/kabbes-real-time-input/
Author: James Kabbes
Author-email: james.kabbes@gmail.com
Project-URL: GitHub, https://github.com/jameskabbes/real_time_input
Project-URL: Documentation, https://jameskabbes.github.io/real_time_input
Classifier: Programming Language :: Python :: 3
Classifier: License :: OSI Approved :: MIT License
Classifier: Operating System :: OS Independent
Requires-Python: >=3.7
License-File: LICENSE
Requires-Dist: kabbes-parent-class
Requires-Dist: kabbes-dir-ops
